irbstudio/__init__.py
irbstudio/main.py
irbstudio/config/__init__.py
irbstudio/config/schema.py
irbstudio/data/__init__.py
irbstudio/data/loader.py
irbstudio/engine/__init__.py
irbstudio/engine/base.py
irbstudio/engine/integrated_analysis.py
irbstudio/engine/mortgage/__init__.py
irbstudio/engine/mortgage/airb_calculator.py
irbstudio/engine/mortgage/sa_calculator.py
irbstudio/reporting/__init__.py
irbstudio/reporting/dashboard.py
irbstudio/simulation/__init__.py
irbstudio/simulation/distribution.py
irbstudio/simulation/migration.py
irbstudio/simulation/portfolio_simulator.py
irbstudio/utils/__init__.py
irbstudio/utils/logging.py
irbstudio-0.1.0.dist-info/licenses/LICENSE
tests/__init__.py
tests/conftest.py
tests/test_advanced_config.py
tests/test_advanced_data_management.py
tests/test_advanced_rwa_calculators.py
tests/test_advanced_simulation.py
tests/test_config_schema.py
tests/test_dashboard.py
tests/test_data_loader.py
tests/test_date_breakdown.py
tests/test_edge_cases.py
tests/test_high_level_api.py
tests/test_integrated_analysis.py
tests/test_integration.py
tests/test_main_api.py
tests/test_memory_efficient.py
tests/test_migration_matrix.py
tests/test_portfolio_simulator.py
tests/test_reporting.py
tests/test_rwa_calculators.py
tests/test_scenario_analysis.py
tests/test_utilities.py
irbstudio-0.1.0.dist-info/METADATA
irbstudio-0.1.0.dist-info/WHEEL
irbstudio-0.1.0.dist-info/top_level.txt
irbstudio-0.1.0.dist-info/RECORD
